lib_back_hubot/__init__.py
lib_back_hubot/formatage.py
lib_back_hubot/function_calcul.py
lib_back_hubot/function_calcul_manager.py
lib_back_hubot/function_calcul_variation.py
lib_back_hubot/function_cubes.py
lib_back_hubot/function_filter_kpi.py
lib_back_hubot/hubot.py
Hubot-0.2.0.dist-info/METADATA
Hubot-0.2.0.dist-info/WHEEL
Hubot-0.2.0.dist-info/top_level.txt
Hubot-0.2.0.dist-info/RECORD
