Metadata-Version: 2.1
Name: Hubot
Version: 0.2.0
Summary: UNKNOWN
Home-page: https://gitlab.com/coddity/hubot/hubot_back
Author: Clément Kérébel
Author-email: clement.kerebel@coddity.com
License: UNKNOWN
Platform: UNKNOWN
Requires-Dist: pandas
Provides-Extra: deployment
Requires-Dist: twine ; extra == 'deployment'
Provides-Extra: test
Requires-Dist: pytest ; extra == 'test'
Requires-Dist: flake8 ; extra == 'test'
